Metadata-Version: 2.0
Name: learnregex
Version: 0.4.11
Summary: A pyschool story for learning regular expressions.
Home-page: https://github.com/sophilabs/learnregex
Author: Sophilabs
Author-email: hi@sophilabs.co
License: MIT license
Keywords: learnregex
Platform: UNKNOWN
Classifier: Development Status :: 2 - Pre-Alpha
Classifier: Intended Audience :: Developers
Classifier: License :: OSI Approved :: MIT License
Classifier: Natural Language :: English
Classifier: Programming Language :: Python :: 3
Classifier: Programming Language :: Python :: 3.3
Classifier: Programming Language :: Python :: 3.4
Classifier: Programming Language :: Python :: 3.5
Requires-Dist: story (>=1.2.2)
